{
  "cartId": "577DFF54-1A86-6F45-7B1B-D5809AB317E0",
  "billingAddress": null,
  "shippingAddress": null,
  "lineItemContainer": {
    "grandTotal": {
      "taxType": "GROSS",
      "formatted": "15,05 €",
      "amount": 15.05,
      "currency": "EUR"
    },
    "totalBeforeTax": {
      "taxType": "NET",
      "formatted": "12,65 €",
      "amount": 12.65,
      "currency": "EUR"
    },
    "totalTax": {
      "taxType": "NONE",
      "formatted": "2,40 €",
      "amount": 2.4,
      "currency": "EUR"
    },
    "lineItemsSubTotal": {
      "taxType": "GROSS",
      "formatted": "12,99 €",
      "amount": 12.99,
      "currency": "EUR"
    },
    "productLineItems": [
      {
        "lineItemId": "577DFF54-4BE8-F266-FF27-D5809AB31749",
        "sku": "Acc-001",
        "name": "Adapter 6,3mm auf 3,5mm",
        "productId": "54E72E1F-746A-8B6E-8E41-0A0C05E64669",
        "quantity": {
          "amount": 1,
          "unit": "piece(s)"
        },
        "lineItemPrice": {
          "taxType": "GROSS",
          "formatted": "12,99 €",
          "amount": 12.99,
          "currency": "EUR"
        },
        "singleItemPrice": {
          "taxType": "GROSS",
          "formatted": "12,99 €",
          "amount": 12.99,
          "currency": "EUR"
        },
        "images": [
          {
            "url": "https://pm.epages.com/WebRoot/Store/Shops/apidocu/54E7/2E1F/746A/8B6E/8E41/0A0C/05E6/4669/acc6_h.jpg",
            "classifier": "HotDeal"
          },
          {
            "url": "https://pm.epages.com/WebRoot/Store/Shops/apidocu/54E7/2E1F/746A/8B6E/8E41/0A0C/05E6/4669/acc6.jpg",
            "classifier": "Large"
          },
          {
            "url": "https://pm.epages.com/WebRoot/Store/Shops/apidocu/54E7/2E1F/746A/8B6E/8E41/0A0C/05E6/4669/acc6_m.jpg",
            "classifier": "Medium"
          },
          {
            "url": "https://pm.epages.com/WebRoot/Store/Shops/apidocu/54E7/2E1F/746A/8B6E/8E41/0A0C/05E6/4669/acc6_s.jpg",
            "classifier": "Small"
          },
          {
            "url": "https://pm.epages.com/WebRoot/Store/Shops/apidocu/54E7/2E1F/746A/8B6E/8E41/0A0C/05E6/4669/acc6_xs.jpg",
            "classifier": "Thumbnail"
          }
        ],
        "links": [
          {
            "rel": "product",
            "href": "https://pm.epages.com/rs/shops/apidocu/products/54E72E1F-746A-8B6E-8E41-0A0C05E64669"
          },
          {
            "rel": "taxClass",
            "href": "https://pm.epages.com/rs/shops/apidocu/tax-classes/5446685F-A8AF-0E18-9B4F-D5809AB30FBF"
          }
        ],
        "essentialFeatures": null,
        "taxClass": {
          "taxClassId": "5446685F-A8AF-0E18-9B4F-D5809AB30FBF",
          "name": "normal",
          "percentage": 19
        },
        "deliveryWeight": {
          "amount": 50,
          "unit": "g"
        }
      }
    ],
    "couponLineItem": {
      "couponLineItemId": "577E01E2-5063-0B06-D5BF-D5809AB34CD3",
      "lineItemPrice": {
        "taxType": "NONE",
        "formatted": "-5,00 €",
        "amount": -5,
        "currency": "EUR"
      }
    },
    "shippingPrice": {
      "taxType": "GROSS",
      "formatted": "7,06 €",
      "amount": 7.06,
      "currency": "EUR"
    }
  },
  "shippingData": {
    "shippingMethod": {
      "id": "5171DD86-C077-0726-C448-AC14145F9026",
      "name": "Standardzustellung"
    },
    "price": {
      "taxType": "GROSS",
      "formatted": "7,06 €",
      "amount": 7.06,
      "currency": "EUR"
    }
  },
  "paymentData": {
    "paymentMethod": {
      "id": "5171DD89-6DE5-E758-E046-AC14145F9009",
      "name": null
    },
    "price": {
      "taxType": "GROSS",
      "formatted": "0,00 €",
      "amount": 0,
      "currency": "EUR"
    }
  },
  "minimumCart": {
    "status": true,
    "code": "SumDiscount",
    "amount": null
  },
  "pickupToken": "YmY1YjU3MTJjZDEwZjM4OThhNWUwMWE1NjdiMDU0ODIzMjM2Y2UwYmEwMzg5ZmU1ZjY2NzQ5OTQ5NTRlNjAzZF8xNDY3ODc1ODEx",
  "checkoutUrl": "https://pm.epages.com/epages/apidocu.sf/?ObjectPath=/Shops/apidocu/AnonymousUsers/3/Baskets/46072&ChangeAction=PickupBasket&PickupToken=YmY1YjU3MTJjZDEwZjM4OThhNWUwMWE1NjdiMDU0ODIzMjM2Y2UwYmEwMzg5ZmU1ZjY2NzQ5OTQ5NTRlNjAzZF8xNDY3ODc1ODEx",
  "links": [
    {
      "rel": "self",
      "href": "https://pm.epages.com/rs/shops/apidocu/carts/577DFF54-1A86-6F45-7B1B-D5809AB317E0"
    },
    {
      "rel": "shipping-method",
      "href": "https://pm.epages.com/rs/shops/apidocu/shipping-methods/5171DD86-C077-0726-C448-AC14145F9026"
    },
    {
      "rel": "remove-coupon",
      "href": "https://pm.epages.com/rs/shops/apidocu/carts/577DFF54-1A86-6F45-7B1B-D5809AB317E0/coupon/577E01E2-5063-0B06-D5BF-D5809AB34CD3"
    }
  ]
}
